where_is/__init__.py
where_is/__version__.py
where_is/arguments.py
where_is/cli.py
where_is/enums.py
where_is/exceptions.py
where_is/structure.py
where_is/utils.py
where_is-0.2.0.dist-info/LICENSE
where_is-0.2.0.dist-info/METADATA
where_is-0.2.0.dist-info/WHEEL
where_is-0.2.0.dist-info/top_level.txt
where_is-0.2.0.dist-info/RECORD
