Metadata-Version: 2.1
Name: where-is
Version: 0.2.0
Summary: A program that helps you find config files (inspired by what-to-code).
Home-page: https://github.com/what-to-code-complete/where-is
Author: ALinuxPerson
Author-email: micheal02052007@gmail.com
License: GNU GPLv3
Platform: UNKNOWN
Classifier: Development Status :: 5 - Production/Stable
Classifier: Environment :: Console
Classifier: Intended Audience :: End Users/Desktop
Classifier: Intended Audience :: System Administrators
Classifier: Intended Audience :: Information Technology
Classifier: License :: OSI Approved :: GNU General Public License v3 or later (GPLv3+)
Classifier: Natural Language :: English
Classifier: Operating System :: POSIX :: Linux
Classifier: Programming Language :: Python :: 3.6
Classifier: Programming Language :: Python :: 3.7
Classifier: Programming Language :: Python :: 3.8
Classifier: Programming Language :: Python :: Implementation :: CPython
Classifier: Topic :: Software Development :: Libraries :: Python Modules
Classifier: Typing :: Typed
Requires-Python: >=3.6.0
Requires-Dist: jsonschema (==3.2.0)
Requires-Dist: termcolor (~=1.1.0)
Requires-Dist: colorama (~=0.4.3)
